MANIFEST.in
setup.py
InsideTrac.egg-info/PKG-INFO
InsideTrac.egg-info/SOURCES.txt
InsideTrac.egg-info/dependency_links.txt
InsideTrac.egg-info/entry_points.txt
InsideTrac.egg-info/requires.txt
InsideTrac.egg-info/top_level.txt
insidetrac/__init__.py
insidetrac/api.py
insidetrac/model.py
insidetrac/templates/insidetrac.user.js
insidetrac/templates/insidetrac_admin.html