Metadata-Version: 1.0
Name: InsideTrac
Version: 0.2.7
Summary: Trac plugin and Greasemonkey scripts to help monitor external projects
Home-page: http://www.insidetrac.org/
Author: Michael J. Pedersen
Author-email: m.pedersen@icelus.org
License: LGPL
Platform: UNKNOWN
